{
  "uid": "9670109",
  "pubdate": "1998 Jun",
  "epubdate": "",
  "source": "J Physiol Pharmacol",
  "authors": [
    {
      "name": "Torlińska T",
      "authtype": "Author",
      "clusterid": ""
    },
    {
      "name": "Maćkowiak P",
      "authtype": "Author",
      "clusterid": ""
    },
    {
      "name": "Nogowski L",
      "authtype": "Author",
      "clusterid": ""
    },
    {
      "name": "Nowak KW",
      "authtype": "Author",
      "clusterid": ""
    },
    {
      "name": "Madry E",
      "authtype": "Author",
      "clusterid": ""
    },
    {
      "name": "Perz M",
      "authtype": "Author",
      "clusterid": ""
    }
  ],
  "lastauthor": "Perz M",
  "title": "Characteristics of insulin receptor binding to various rat tissues.",
  "sorttitle": "characteristics of insulin receptor binding to various rat tissues",
  "volume": "49",
  "issue": "2",
  "pages": "261-70",
  "lang": [
    "eng"
  ],
  "nlmuniqueid": "9114501",
  "issn": "0867-5910",
  "essn": "",
  "pubtype": [
    "Comparative Study",
    "Journal Article"
  ],
  "recordstatus": "PubMed - indexed for MEDLINE",
  "pubstatus": "4",
  "articleids": [
    {
      "idtype": "pubmed",
      "idtypen": 1,
      "value": "9670109"
    }
  ],
  "history": [
    {
      "pubstatus": "pubmed",
      "date": "1998/07/22 00:00"
    },
    {
      "pubstatus": "medline",
      "date": "1998/07/22 00:01"
    },
    {
      "pubstatus": "entrez",
      "date": "1998/07/22 00:00"
    }
  ],
  "references": [],
  "attributes": [
    "Has Abstract"
  ],
  "pmcrefcount": "",
  "fulljournalname": "Journal of physiology and pharmacology : an official journal of the Polish Physiological Society",
  "elocationid": "",
  "doctype": "citation",
  "srccontriblist": [],
  "booktitle": "",
  "medium": "",
  "edition": "",
  "publisherlocation": "",
  "publishername": "",
  "srcdate": "",
  "reportnumber": "",
  "availablefromurl": "",
  "locationlabel": "",
  "doccontriblist": [],
  "docdate": "",
  "bookname": "",
  "chapter": "",
  "sortpubdate": "1998/06/01 00:00",
  "sortfirstauthor": "Torlińska T",
  "vernaculartitle": ""
}