{
  "uid": "40437139",
  "pubdate": "2025 May",
  "epubdate": "2025 May 28",
  "source": "Nat Comput Sci",
  "authors": [
    {
      "name": "Sacha M",
      "authtype": "Author",
      "clusterid": ""
    },
    {
      "name": "Tesler F",
      "authtype": "Author",
      "clusterid": ""
    },
    {
      "name": "Cofre R",
      "authtype": "Author",
      "clusterid": ""
    },
    {
      "name": "Destexhe A",
      "authtype": "Author",
      "clusterid": ""
    }
  ],
  "lastauthor": "Destexhe A",
  "title": "A computational approach to evaluate how molecular mechanisms impact large-scale brain activity.",
  "sorttitle": "computational approach to evaluate how molecular mechanisms impact large scale brain activity",
  "volume": "5",
  "issue": "5",
  "pages": "405-417",
  "lang": [
    "eng"
  ],
  "nlmuniqueid": "101775476",
  "issn": "",
  "essn": "2662-8457",
  "pubtype": [
    "Journal Article",
    "Research Support, Non-U.S. Gov't"
  ],
  "recordstatus": "PubMed - indexed for MEDLINE",
  "pubstatus": "256",
  "articleids": [
    {
      "idtype": "pubmed",
      "idtypen": 1,
      "value": "40437139"
    },
    {
      "idtype": "pmc",
      "idtypen": 8,
      "value": "PMC12119344"
    },
    {
      "idtype": "pmcid",
      "idtypen": 5,
      "value": "pmc-id: PMC12119344;"
    },
    {
      "idtype": "doi",
      "idtypen": 3,
      "value": "10.1038/s43588-025-00796-8"
    },
    {
      "idtype": "pii",
      "idtypen": 4,
      "value": "10.1038/s43588-025-00796-8"
    }
  ],
  "history": [
    {
      "pubstatus": "received",
      "date": "2024/06/20 00:00"
    },
    {
      "pubstatus": "accepted",
      "date": "2025/03/21 00:00"
    },
    {
      "pubstatus": "medline",
      "date": "2025/05/29 00:28"
    },
    {
      "pubstatus": "pubmed",
      "date": "2025/05/29 00:27"
    },
    {
      "pubstatus": "entrez",
      "date": "2025/05/28 23:31"
    },
    {
      "pubstatus": "pmc-release",
      "date": "2025/05/28 00:00"
    }
  ],
  "references": [],
  "attributes": [
    "Has Abstract"
  ],
  "pmcrefcount": 62,
  "fulljournalname": "Nature computational science",
  "elocationid": "doi: 10.1038/s43588-025-00796-8",
  "doctype": "citation",
  "srccontriblist": [],
  "booktitle": "",
  "medium": "",
  "edition": "",
  "publisherlocation": "",
  "publishername": "",
  "srcdate": "",
  "reportnumber": "",
  "availablefromurl": "",
  "locationlabel": "",
  "doccontriblist": [],
  "docdate": "",
  "bookname": "",
  "chapter": "",
  "sortpubdate": "2025/05/01 00:00",
  "sortfirstauthor": "Sacha M",
  "vernaculartitle": ""
}