{
  "id": "https://openalex.org/W4389734083",
  "doi": "https://doi.org/10.3389/fpsyt.2023.1267583",
  "title": "Health-related quality of life and family functioning of primary caregivers of children with down syndrome",
  "display_name": "Health-related quality of life and family functioning of primary caregivers of children with down syndrome",
  "publication_year": 2023,
  "publication_date": "2023-12-14",
  "ids": {
    "openalex": "https://openalex.org/W4389734083",
    "doi": "https://doi.org/10.3389/fpsyt.2023.1267583",
    "pmid": "https://pubmed.ncbi.nlm.nih.gov/38161724"
  },
  "language": "en",
  "primary_location": {
    "id": "doi:10.3389/fpsyt.2023.1267583",
    "is_oa": true,
    "landing_page_url": "https://doi.org/10.3389/fpsyt.2023.1267583",
    "pdf_url": "https://www.frontiersin.org/journals/psychiatry/articles/10.3389/fpsyt.2023.1267583/pdf",
    "source": {
      "id": "https://openalex.org/S92766711",
      "display_name": "Frontiers in Psychiatry",
      "issn_l": "1664-0640",
      "issn": [
        "1664-0640"
      ],
      "is_oa": true,
      "is_in_doaj": true,
      "is_core": true,
      "host_organization": "https://openalex.org/P4310320527",
      "host_organization_name": "Frontiers Media",
      "host_organization_lineage": [
        "https://openalex.org/P4310320527"
      ],
      "host_organization_lineage_names": [
        "Frontiers Media"
      ],
      "type": "journal"
    },
    "license": "cc-by",
    "license_id": "https://openalex.org/licenses/cc-by",
    "version": "publishedVersion",
    "is_accepted": true,
    "is_published": true,
    "raw_source_name": "Frontiers in Psychiatry",
    "raw_type": "journal-article"
  },
  "type": "article",
  "indexed_in": [
    "crossref",
    "doaj",
    "pubmed"
  ],
  "open_access": {
    "is_oa": true,
    "oa_status": "gold",
    "oa_url": "https://www.frontiersin.org/journals/psychiatry/articles/10.3389/fpsyt.2023.1267583/pdf",
    "any_repository_has_fulltext": true
  },
  "authorships": [
    {
      "author_position": "first",
      "author": {
        "id": "https://openalex.org/A5080061188",
        "display_name": "Anna Rozensztrauch",
        "orcid": null
      },
      "institutions": [
        {
          "id": "https://openalex.org/I385303915",
          "display_name": "Wroclaw Medical University",
          "ror": "https://ror.org/01qpw1b93",
          "country_code": "PL",
          "type": "education",
          "lineage": [
            "https://openalex.org/I385303915"
          ]
        }
      ],
      "countries": [
        "PL"
      ],
      "is_corresponding": true,
      "raw_author_name": "Anna Rozensztrauch",
      "raw_affiliation_strings": [
        "Clinical Department of Pediatrics, Endocrinology, Diabetology and Metabolic Diseases, Wroclaw Medical University, Wroclaw, Poland"
      ],
      "raw_orcid": null,
      "affiliations": [
        {
          "raw_affiliation_string": "Clinical Department of Pediatrics, Endocrinology, Diabetology and Metabolic Diseases, Wroclaw Medical University, Wroclaw, Poland",
          "institution_ids": [
            "https://openalex.org/I385303915"
          ]
        }
      ]
    },
    {
      "author_position": "middle",
      "author": {
        "id": "https://openalex.org/A5072745415",
        "display_name": "Karolina Wieczorek",
        "orcid": "https://orcid.org/0000-0002-8736-9796"
      },
      "institutions": [
        {
          "id": "https://openalex.org/I385303915",
          "display_name": "Wroclaw Medical University",
          "ror": "https://ror.org/01qpw1b93",
          "country_code": "PL",
          "type": "education",
          "lineage": [
            "https://openalex.org/I385303915"
          ]
        }
      ],
      "countries": [
        "PL"
      ],
      "is_corresponding": false,
      "raw_author_name": "Karolina Wieczorek",
      "raw_affiliation_strings": [
        "Clinical Department of Pediatrics, Endocrinology, Diabetology and Metabolic Diseases, Wroclaw Medical University, Wroclaw, Poland"
      ],
      "raw_orcid": null,
      "affiliations": [
        {
          "raw_affiliation_string": "Clinical Department of Pediatrics, Endocrinology, Diabetology and Metabolic Diseases, Wroclaw Medical University, Wroclaw, Poland",
          "institution_ids": [
            "https://openalex.org/I385303915"
          ]
        }
      ]
    },
    {
      "author_position": "middle",
      "author": {
        "id": "https://openalex.org/A5093367931",
        "display_name": "Iwona Twardak",
        "orcid": "https://orcid.org/0000-0001-6990-5738"
      },
      "institutions": [
        {
          "id": "https://openalex.org/I385303915",
          "display_name": "Wroclaw Medical University",
          "ror": "https://ror.org/01qpw1b93",
          "country_code": "PL",
          "type": "education",
          "lineage": [
            "https://openalex.org/I385303915"
          ]
        }
      ],
      "countries": [
        "PL"
      ],
      "is_corresponding": false,
      "raw_author_name": "Iwona Twardak",
      "raw_affiliation_strings": [
        "Clinical Department of Pediatrics, Endocrinology, Diabetology and Metabolic Diseases, Wroclaw Medical University, Wroclaw, Poland"
      ],
      "raw_orcid": null,
      "affiliations": [
        {
          "raw_affiliation_string": "Clinical Department of Pediatrics, Endocrinology, Diabetology and Metabolic Diseases, Wroclaw Medical University, Wroclaw, Poland",
          "institution_ids": [
            "https://openalex.org/I385303915"
          ]
        }
      ]
    },
    {
      "author_position": "last",
      "author": {
        "id": "https://openalex.org/A5037180800",
        "display_name": "Robert Śmigiel",
        "orcid": "https://orcid.org/0000-0003-2930-9549"
      },
      "institutions": [
        {
          "id": "https://openalex.org/I385303915",
          "display_name": "Wroclaw Medical University",
          "ror": "https://ror.org/01qpw1b93",
          "country_code": "PL",
          "type": "education",
          "lineage": [
            "https://openalex.org/I385303915"
          ]
        }
      ],
      "countries": [
        "PL"
      ],
      "is_corresponding": false,
      "raw_author_name": "Robert Śmigiel",
      "raw_affiliation_strings": [
        "Clinical Department of Pediatrics, Endocrinology, Diabetology and Metabolic Diseases, Wroclaw Medical University, Wroclaw, Poland"
      ],
      "raw_orcid": null,
      "affiliations": [
        {
          "raw_affiliation_string": "Clinical Department of Pediatrics, Endocrinology, Diabetology and Metabolic Diseases, Wroclaw Medical University, Wroclaw, Poland",
          "institution_ids": [
            "https://openalex.org/I385303915"
          ]
        }
      ]
    }
  ],
  "institutions": [],
  "countries_distinct_count": 1,
  "institutions_distinct_count": 4,
  "corresponding_author_ids": [
    "https://openalex.org/A5080061188"
  ],
  "corresponding_institution_ids": [
    "https://openalex.org/I385303915"
  ],
  "apc_list": {
    "value": 2950,
    "currency": "USD",
    "value_usd": 2950
  },
  "apc_paid": {
    "value": 2950,
    "currency": "USD",
    "value_usd": 2950
  },
  "fwci": 2.342,
  "has_fulltext": true,
  "cited_by_count": 8,
  "citation_normalized_percentile": {
    "value": 0.88536148,
    "is_in_top_1_percent": false,
    "is_in_top_10_percent": false
  },
  "cited_by_percentile_year": {
    "min": 95,
    "max": 98
  },
  "biblio": {
    "volume": "14",
    "issue": null,
    "first_page": "1267583",
    "last_page": "1267583"
  },
  "is_retracted": false,
  "is_paratext": false,
  "is_xpac": false,
  "primary_topic": {
    "id": "https://openalex.org/T11632",
    "display_name": "Family and Disability Support Research",
    "score": 0.7405999898910522,
    "subfield": {
      "id": "https://openalex.org/subfields/3203",
      "display_name": "Clinical Psychology"
    },
    "field": {
      "id": "https://openalex.org/fields/32",
      "display_name": "Psychology"
    },
    "domain": {
      "id": "https://openalex.org/domains/2",
      "display_name": "Social Sciences"
    }
  },
  "topics": [
    {
      "id": "https://openalex.org/T11632",
      "display_name": "Family and Disability Support Research",
      "score": 0.7405999898910522,
      "subfield": {
        "id": "https://openalex.org/subfields/3203",
        "display_name": "Clinical Psychology"
      },
      "field": {
        "id": "https://openalex.org/fields/32",
        "display_name": "Psychology"
      },
      "domain": {
        "id": "https://openalex.org/domains/2",
        "display_name": "Social Sciences"
      }
    },
    {
      "id": "https://openalex.org/T11015",
      "display_name": "Down syndrome and intellectual disability research",
      "score": 0.17720000445842743,
      "subfield": {
        "id": "https://openalex.org/subfields/2739",
        "display_name": "Public Health, Environmental and Occupational Health"
      },
      "field": {
        "id": "https://openalex.org/fields/27",
        "display_name": "Medicine"
      },
      "domain": {
        "id": "https://openalex.org/domains/4",
        "display_name": "Health Sciences"
      }
    },
    {
      "id": "https://openalex.org/T11003",
      "display_name": "Disability Rights and Representation",
      "score": 0.007199999876320362,
      "subfield": {
        "id": "https://openalex.org/subfields/3311",
        "display_name": "Safety Research"
      },
      "field": {
        "id": "https://openalex.org/fields/33",
        "display_name": "Social Sciences"
      },
      "domain": {
        "id": "https://openalex.org/domains/2",
        "display_name": "Social Sciences"
      }
    }
  ],
  "keywords": [
    {
      "id": "https://openalex.org/keywords/quality-of-life",
      "display_name": "Quality of life (healthcare)",
      "score": 0.5254475474357605
    },
    {
      "id": "https://openalex.org/keywords/medicine",
      "display_name": "Medicine",
      "score": 0.47666671872138977
    },
    {
      "id": "https://openalex.org/keywords/psychology",
      "display_name": "Psychology",
      "score": 0.4553752839565277
    },
    {
      "id": "https://openalex.org/keywords/psychiatry",
      "display_name": "Psychiatry",
      "score": 0.43375590443611145
    },
    {
      "id": "https://openalex.org/keywords/down-syndrome",
      "display_name": "Down syndrome",
      "score": 0.41625940799713135
    },
    {
      "id": "https://openalex.org/keywords/gerontology",
      "display_name": "Gerontology",
      "score": 0.36650028824806213
    },
    {
      "id": "https://openalex.org/keywords/clinical-psychology",
      "display_name": "Clinical psychology",
      "score": 0.33179980516433716
    },
    {
      "id": "https://openalex.org/keywords/nursing",
      "display_name": "Nursing",
      "score": 0.15409612655639648
    }
  ],
  "concepts": [
    {
      "id": "https://openalex.org/C2779951463",
      "wikidata": "https://www.wikidata.org/wiki/Q7268788",
      "display_name": "Quality of life (healthcare)",
      "level": 2,
      "score": 0.5254475474357605
    },
    {
      "id": "https://openalex.org/C71924100",
      "wikidata": "https://www.wikidata.org/wiki/Q11190",
      "display_name": "Medicine",
      "level": 0,
      "score": 0.47666671872138977
    },
    {
      "id": "https://openalex.org/C15744967",
      "wikidata": "https://www.wikidata.org/wiki/Q9418",
      "display_name": "Psychology",
      "level": 0,
      "score": 0.4553752839565277
    },
    {
      "id": "https://openalex.org/C118552586",
      "wikidata": "https://www.wikidata.org/wiki/Q7867",
      "display_name": "Psychiatry",
      "level": 1,
      "score": 0.43375590443611145
    },
    {
      "id": "https://openalex.org/C2779954681",
      "wikidata": "https://www.wikidata.org/wiki/Q47715",
      "display_name": "Down syndrome",
      "level": 2,
      "score": 0.41625940799713135
    },
    {
      "id": "https://openalex.org/C74909509",
      "wikidata": "https://www.wikidata.org/wiki/Q10387",
      "display_name": "Gerontology",
      "level": 1,
      "score": 0.36650028824806213
    },
    {
      "id": "https://openalex.org/C70410870",
      "wikidata": "https://www.wikidata.org/wiki/Q199906",
      "display_name": "Clinical psychology",
      "level": 1,
      "score": 0.33179980516433716
    },
    {
      "id": "https://openalex.org/C159110408",
      "wikidata": "https://www.wikidata.org/wiki/Q121176",
      "display_name": "Nursing",
      "level": 1,
      "score": 0.15409612655639648
    }
  ],
  "mesh": [],
  "locations_count": 4,
  "locations": [
    {
      "id": "doi:10.3389/fpsyt.2023.1267583",
      "is_oa": true,
      "landing_page_url": "https://doi.org/10.3389/fpsyt.2023.1267583",
      "pdf_url": "https://www.frontiersin.org/journals/psychiatry/articles/10.3389/fpsyt.2023.1267583/pdf",
      "source": {
        "id": "https://openalex.org/S92766711",
        "display_name": "Frontiers in Psychiatry",
        "issn_l": "1664-0640",
        "issn": [
          "1664-0640"
        ],
        "is_oa": true,
        "is_in_doaj": true,
        "is_core": true,
        "host_organization": "https://openalex.org/P4310320527",
        "host_organization_name": "Frontiers Media",
        "host_organization_lineage": [
          "https://openalex.org/P4310320527"
        ],
        "host_organization_lineage_names": [
          "Frontiers Media"
        ],
        "type": "journal"
      },
      "license": "cc-by",
      "license_id": "https://openalex.org/licenses/cc-by",
      "version": "publishedVersion",
      "is_accepted": true,
      "is_published": true,
      "raw_source_name": "Frontiers in Psychiatry",
      "raw_type": "journal-article"
    },
    {
      "id": "pmid:38161724",
      "is_oa": false,
      "landing_page_url": "https://pubmed.ncbi.nlm.nih.gov/38161724",
      "pdf_url": null,
      "source": {
        "id": "https://openalex.org/S4306525036",
        "display_name": "PubMed",
        "issn_l": null,
        "issn": null,
        "is_oa": false,
        "is_in_doaj": false,
        "is_core": false,
        "host_organization": "https://openalex.org/I1299303238",
        "host_organization_name": "National Institutes of Health",
        "host_organization_lineage": [
          "https://openalex.org/I1299303238"
        ],
        "host_organization_lineage_names": [],
        "type": "repository"
      },
      "license": null,
      "license_id": null,
      "version": "publishedVersion",
      "is_accepted": true,
      "is_published": true,
      "raw_source_name": "Frontiers in psychiatry",
      "raw_type": null
    },
    {
      "id": "pmh:oai:pubmedcentral.nih.gov:10756234",
      "is_oa": true,
      "landing_page_url": "https://www.ncbi.nlm.nih.gov/pmc/articles/10756234",
      "pdf_url": "https://pmc.ncbi.nlm.nih.gov/articles/PMC10756234/pdf/fpsyt-14-1267583.pdf",
      "source": {
        "id": "https://openalex.org/S2764455111",
        "display_name": "PubMed Central",
        "issn_l": null,
        "issn": null,
        "is_oa": true,
        "is_in_doaj": false,
        "is_core": false,
        "host_organization": "https://openalex.org/I1299303238",
        "host_organization_name": "National Institutes of Health",
        "host_organization_lineage": [
          "https://openalex.org/I1299303238"
        ],
        "host_organization_lineage_names": [],
        "type": "repository"
      },
      "license": "cc-by",
      "license_id": "https://openalex.org/licenses/cc-by",
      "version": "submittedVersion",
      "is_accepted": false,
      "is_published": false,
      "raw_source_name": "Front Psychiatry",
      "raw_type": "Text"
    },
    {
      "id": "pmh:oai:doaj.org/article:6a0da6974cac4b95a646be0d6c9dd2ed",
      "is_oa": true,
      "landing_page_url": "https://doaj.org/article/6a0da6974cac4b95a646be0d6c9dd2ed",
      "pdf_url": null,
      "source": {
        "id": "https://openalex.org/S4306401280",
        "display_name": "DOAJ (DOAJ: Directory of Open Access Journals)",
        "issn_l": null,
        "issn": null,
        "is_oa": false,
        "is_in_doaj": false,
        "is_core": false,
        "host_organization": null,
        "host_organization_name": null,
        "host_organization_lineage": [],
        "host_organization_lineage_names": [],
        "type": "repository"
      },
      "license": "cc-by-sa",
      "license_id": "https://openalex.org/licenses/cc-by-sa",
      "version": "submittedVersion",
      "is_accepted": false,
      "is_published": false,
      "raw_source_name": "Frontiers in Psychiatry, Vol 14 (2023)",
      "raw_type": "article"
    }
  ],
  "best_oa_location": {
    "id": "doi:10.3389/fpsyt.2023.1267583",
    "is_oa": true,
    "landing_page_url": "https://doi.org/10.3389/fpsyt.2023.1267583",
    "pdf_url": "https://www.frontiersin.org/journals/psychiatry/articles/10.3389/fpsyt.2023.1267583/pdf",
    "source": {
      "id": "https://openalex.org/S92766711",
      "display_name": "Frontiers in Psychiatry",
      "issn_l": "1664-0640",
      "issn": [
        "1664-0640"
      ],
      "is_oa": true,
      "is_in_doaj": true,
      "is_core": true,
      "host_organization": "https://openalex.org/P4310320527",
      "host_organization_name": "Frontiers Media",
      "host_organization_lineage": [
        "https://openalex.org/P4310320527"
      ],
      "host_organization_lineage_names": [
        "Frontiers Media"
      ],
      "type": "journal"
    },
    "license": "cc-by",
    "license_id": "https://openalex.org/licenses/cc-by",
    "version": "publishedVersion",
    "is_accepted": true,
    "is_published": true,
    "raw_source_name": "Frontiers in Psychiatry",
    "raw_type": "journal-article"
  },
  "sustainable_development_goals": [
    {
      "score": 0.47999998927116394,
      "id": "https://metadata.un.org/sdg/4",
      "display_name": "Quality Education"
    }
  ],
  "awards": [],
  "funders": [],
  "has_content": {
    "grobid_xml": false,
    "pdf": true
  },
  "content_urls": {
    "pdf": "https://content.openalex.org/works/W4389734083.pdf"
  },
  "referenced_works_count": 43,
  "referenced_works": [
    "https://openalex.org/W29536382",
    "https://openalex.org/W1517371674",
    "https://openalex.org/W1537021500",
    "https://openalex.org/W1551651079",
    "https://openalex.org/W1587246273",
    "https://openalex.org/W1644542855",
    "https://openalex.org/W1743708126",
    "https://openalex.org/W1988169760",
    "https://openalex.org/W1997217133",
    "https://openalex.org/W2013491255",
    "https://openalex.org/W2046840784",
    "https://openalex.org/W2050878694",
    "https://openalex.org/W2095112879",
    "https://openalex.org/W2116690507",
    "https://openalex.org/W2117733065",
    "https://openalex.org/W2121614161",
    "https://openalex.org/W2129813778",
    "https://openalex.org/W2136271495",
    "https://openalex.org/W2139695087",
    "https://openalex.org/W2151734850",
    "https://openalex.org/W2323149989",
    "https://openalex.org/W2549295509",
    "https://openalex.org/W2579409834",
    "https://openalex.org/W2738617921",
    "https://openalex.org/W2768747276",
    "https://openalex.org/W2792746365",
    "https://openalex.org/W2807872580",
    "https://openalex.org/W2896450360",
    "https://openalex.org/W2904875251",
    "https://openalex.org/W2920830189",
    "https://openalex.org/W2944258205",
    "https://openalex.org/W2971499594",
    "https://openalex.org/W2980801468",
    "https://openalex.org/W3007508876",
    "https://openalex.org/W3035379247",
    "https://openalex.org/W3090989081",
    "https://openalex.org/W3121047671",
    "https://openalex.org/W3207797274",
    "https://openalex.org/W4210691315",
    "https://openalex.org/W4237822883",
    "https://openalex.org/W6730062441",
    "https://openalex.org/W6769323099",
    "https://openalex.org/W6943771503"
  ],
  "related_works": [
    "https://openalex.org/W1978714716",
    "https://openalex.org/W2996130271",
    "https://openalex.org/W3094188746",
    "https://openalex.org/W2170737663",
    "https://openalex.org/W2980418207",
    "https://openalex.org/W2465513794",
    "https://openalex.org/W4245106712",
    "https://openalex.org/W1971546783",
    "https://openalex.org/W13239102",
    "https://openalex.org/W1531361161"
  ],
  "abstract_inverted_index": {
    "Background": [
      0
    ],
    "Down": [
      1
    ],
    "Syndrome": [
      2
    ],
    "(DS;": [
      3
    ],
    "OMIM": [
      4
    ],
    "#190685),": [
      5
    ],
    "known": [
      6,
      25
    ],
    "as": [
      7,
      254,
      256
    ],
    "trisomy": [
      8,
      64,
      90,
      235,
      298
    ],
    "21,": [
      9
    ],
    "is": [
      10,
      237,
      279
    ],
    "one": [
      11
    ],
    "of": [
      12,
      27,
      38,
      41,
      53,
      59,
      61,
      69,
      87,
      123,
      127,
      136,
      184,
      230,
      232,
      251,
      260,
      273,
      286,
      292,
      294
    ],
    "the": [
      13,
      19,
      23,
      36,
      57,
      67,
      70,
      73,
      98,
      105,
      137,
      145,
      148,
      161,
      194,
      198,
      228,
      245,
      249,
      257,
      261,
      271,
      276,
      287,
      309
    ],
    "most": [
      14
    ],
    "common": [
      15
    ],
    "genetic": [
      16,
      139
    ],
    "disorders": [
      17
    ],
    "in": [
      18,
      197,
      270,
      296
    ],
    "human": [
      20
    ],
    "population": [
      21
    ],
    "and": [
      22,
      46,
      66,
      111,
      160,
      214,
      248,
      275,
      305
    ],
    "commonest": [
      24
    ],
    "cause": [
      26
    ],
    "intellectual": [
      28
    ],
    "disability.": [
      29
    ],
    "The": [
      30,
      82,
      92,
      116,
      182,
      289
    ],
    "study": [
      31,
      54
    ],
    "was": [
      32,
      152,
      163,
      178,
      240
    ],
    "conducted": [
      33
    ],
    "to": [
      34,
      282
    ],
    "investigate": [
      35
    ],
    "quality": [
      37,
      58,
      229
    ],
    "life": [
      39,
      60,
      231
    ],
    "(QoL)": [
      40
    ],
    "children": [
      42,
      62,
      88,
      233
    ],
    "with": [
      43,
      63,
      89,
      119,
      234
    ],
    "DS": [
      44
    ],
    "syndrome": [
      45
    ],
    "its": [
      47
    ],
    "impact": [
      48,
      68,
      135,
      192
    ],
    "on": [
      49,
      72,
      141,
      193
    ],
    "family": [
      50,
      142,
      277
    ],
    "functioning.": [
      51,
      143
    ],
    "Purpose": [
      52
    ],
    "To": [
      55
    ],
    "assess": [
      56
    ],
    "21": [
      65,
      236,
      299
    ],
    "disorder": [
      71
    ],
    "family.": [
      74,
      264
    ],
    "Methods": [
      75
    ],
    "We": [
      76
    ],
    "used": [
      77
    ],
    "a": [
      78,
      120,
      128,
      133,
      190,
      241
    ],
    "cross-sectional": [
      79
    ],
    "questionnaire": [
      80
    ],
    "study.": [
      81
    ],
    "respondents": [
      83
    ],
    "were": [
      84,
      96
    ],
    "52": [
      85
    ],
    "parents": [
      86,
      274
    ],
    "21.": [
      91
    ],
    "following": [
      93
    ],
    "structured": [
      94
    ],
    "questionnaires": [
      95
    ],
    "used:": [
      97
    ],
    "PedsQL": [
      99,
      106
    ],
    "™": [
      100,
      107
    ],
    "4.0": [
      101
    ],
    "Generic": [
      102
    ],
    "Core": [
      103
    ],
    "Scales,": [
      104
    ],
    "Family": [
      108
    ],
    "Impact": [
      109
    ],
    "Module": [
      110
    ],
    "Study-Specific": [
      112
    ],
    "Questionnaire": [
      113
    ],
    "(SSQ).": [
      114
    ],
    "Results": [
      115
    ],
    "combined": [
      117
    ],
    "scores,": [
      118
    ],
    "mean": [
      121
    ],
    "value": [
      122
    ],
    "approximately": [
      124
    ],
    "55": [
      125
    ],
    "out": [
      126
    ],
    "possible": [
      129
    ],
    "100": [
      130
    ],
    "points,": [
      131
    ],
    "indicated": [
      132
    ],
    "significant": [
      134
    ],
    "child’s": [
      138,
      195,
      246,
      262
    ],
    "defect": [
      140
    ],
    "In": [
      144
    ],
    "overall": [
      146,
      215
    ],
    "QOL,": [
      147
    ],
    "highest": [
      149
    ],
    "rated": [
      150
    ],
    "domain": [
      151
    ],
    "physical": [
      153,
      199
    ],
    "functioning": [
      154,
      165,
      173,
      196,
      259,
      278
    ],
    "(x̅": [
      155,
      166
    ],
    "=60.14;": [
      156
    ],
    "SD": [
      157,
      168
    ],
    "=": [
      158,
      169,
      176,
      202,
      207,
      212,
      220
    ],
    "23.82)": [
      159
    ],
    "lowest": [
      162
    ],
    "school": [
      164,
      172
    ],
    "=51.36;": [
      167
    ],
    "18.72).": [
      170
    ],
    "Better": [
      171
    ],
    "(": [
      174,
      200,
      205,
      210,
      218
    ],
    "p": [
      175,
      201,
      206,
      211,
      219
    ],
    "0.022)": [
      177
    ],
    "reported": [
      179
    ],
    "for": [
      180,
      302,
      308
    ],
    "girls.": [
      181
    ],
    "presence": [
      183
    ],
    "reduced": [
      185
    ],
    "muscle": [
      186
    ],
    "tone": [
      187
    ],
    "also": [
      188
    ],
    "had": [
      189
    ],
    "negative": [
      191
    ],
    "0.036),": [
      203
    ],
    "emotional": [
      204
    ],
    "0.011),": [
      208
    ],
    "psychosocial": [
      209
    ],
    "0.027)": [
      213
    ],
    "QOL": [
      216,
      247,
      250,
      272,
      285,
      295
    ],
    "domains": [
      217
    ],
    "0.023).": [
      221
    ],
    "Conclusion": [
      222
    ],
    "Overall,": [
      223
    ],
    "our": [
      224
    ],
    "results": [
      225
    ],
    "showed": [
      226
    ],
    "that": [
      227
    ],
    "impaired.": [
      238
    ],
    "There": [
      239
    ],
    "positive": [
      242
    ],
    "association": [
      243
    ],
    "between": [
      244
    ],
    "their": [
      252
    ],
    "parents,": [
      253
    ],
    "well": [
      255
    ],
    "general": [
      258
    ],
    "whole": [
      263
    ],
    "For": [
      265
    ],
    "this": [
      266
    ],
    "reason,": [
      267
    ],
    "an": [
      268,
      283
    ],
    "improvement": [
      269
    ],
    "closely": [
      280
    ],
    "related": [
      281
    ],
    "increased": [
      284
    ],
    "child.": [
      288
    ],
    "continuous": [
      290
    ],
    "deepening": [
      291
    ],
    "knowledge": [
      293
    ],
    "individual": [
      297
    ],
    "management": [
      300
    ],
    "allows": [
      301
    ],
    "better": [
      303
    ],
    "preparation": [
      304
    ],
    "ongoing": [
      306
    ],
    "care": [
      307
    ],
    "patients": [
      310
    ],
    "concerned.": [
      311
    ]
  },
  "counts_by_year": [
    {
      "year": 2026,
      "cited_by_count": 1
    },
    {
      "year": 2025,
      "cited_by_count": 2
    },
    {
      "year": 2024,
      "cited_by_count": 5
    }
  ],
  "updated_date": "2026-06-12T08:23:45.883708",
  "created_date": "2025-10-10T00:00:00"
}