{
  "uid": "40930532",
  "pubdate": "2025 Sep 5",
  "epubdate": "",
  "source": "Nucleic Acids Res",
  "authors": [
    {
      "name": "Landrock MF",
      "authtype": "Author",
      "clusterid": ""
    },
    {
      "name": "Krutyhołowa R",
      "authtype": "Author",
      "clusterid": ""
    },
    {
      "name": "Böhnert P",
      "authtype": "Author",
      "clusterid": ""
    },
    {
      "name": "Mazur J",
      "authtype": "Author",
      "clusterid": ""
    },
    {
      "name": "Honc M",
      "authtype": "Author",
      "clusterid": ""
    },
    {
      "name": "Hammermeister A",
      "authtype": "Author",
      "clusterid": ""
    },
    {
      "name": "Bessler L",
      "authtype": "Author",
      "clusterid": ""
    },
    {
      "name": "Scherf D",
      "authtype": "Author",
      "clusterid": ""
    },
    {
      "name": "Elms A",
      "authtype": "Author",
      "clusterid": ""
    },
    {
      "name": "Radczuk N",
      "authtype": "Author",
      "clusterid": ""
    },
    {
      "name": "Skupien-Rabian B",
      "authtype": "Author",
      "clusterid": ""
    },
    {
      "name": "Jankowska U",
      "authtype": "Author",
      "clusterid": ""
    },
    {
      "name": "Herberg FW",
      "authtype": "Author",
      "clusterid": ""
    },
    {
      "name": "Helm M",
      "authtype": "Author",
      "clusterid": ""
    },
    {
      "name": "Klassen R",
      "authtype": "Author",
      "clusterid": ""
    },
    {
      "name": "Glatt S",
      "authtype": "Author",
      "clusterid": ""
    },
    {
      "name": "Schaffrath R",
      "authtype": "Author",
      "clusterid": ""
    }
  ],
  "lastauthor": "Schaffrath R",
  "title": "Autophosphorylation of conserved yeast and human casein kinase 1 isozymes regulates Elongator-dependent tRNA modifications.",
  "sorttitle": "autophosphorylation of conserved yeast and human casein kinase 1 isozymes regulates elongator dependent trna modifications",
  "volume": "53",
  "issue": "17",
  "pages": "",
  "lang": [
    "eng"
  ],
  "nlmuniqueid": "0411011",
  "issn": "0305-1048",
  "essn": "1362-4962",
  "pubtype": [
    "Journal Article"
  ],
  "recordstatus": "PubMed - indexed for MEDLINE",
  "pubstatus": "4",
  "articleids": [
    {
      "idtype": "pubmed",
      "idtypen": 1,
      "value": "40930532"
    },
    {
      "idtype": "pmc",
      "idtypen": 8,
      "value": "PMC12421383"
    },
    {
      "idtype": "pmcid",
      "idtypen": 5,
      "value": "pmc-id: PMC12421383;"
    },
    {
      "idtype": "doi",
      "idtypen": 3,
      "value": "10.1093/nar/gkaf881"
    },
    {
      "idtype": "pii",
      "idtypen": 4,
      "value": "8250478"
    }
  ],
  "history": [
    {
      "pubstatus": "accepted",
      "date": "2025/08/20 00:00"
    },
    {
      "pubstatus": "revised",
      "date": "2025/08/12 00:00"
    },
    {
      "pubstatus": "received",
      "date": "2024/07/23 00:00"
    },
    {
      "pubstatus": "medline",
      "date": "2025/09/11 00:29"
    },
    {
      "pubstatus": "pubmed",
      "date": "2025/09/11 00:28"
    },
    {
      "pubstatus": "entrez",
      "date": "2025/09/10 20:15"
    },
    {
      "pubstatus": "pmc-release",
      "date": "2025/09/10 00:00"
    }
  ],
  "references": [],
  "attributes": [
    "Has Abstract"
  ],
  "pmcrefcount": 119,
  "fulljournalname": "Nucleic acids research",
  "elocationid": "doi: 10.1093/nar/gkaf881",
  "doctype": "citation",
  "srccontriblist": [],
  "booktitle": "",
  "medium": "",
  "edition": "",
  "publisherlocation": "",
  "publishername": "",
  "srcdate": "",
  "reportnumber": "",
  "availablefromurl": "",
  "locationlabel": "",
  "doccontriblist": [],
  "docdate": "",
  "bookname": "",
  "chapter": "",
  "sortpubdate": "2025/09/05 00:00",
  "sortfirstauthor": "Landrock MF",
  "vernaculartitle": ""
}