{
  "uid": "42095410",
  "pubdate": "2026 May 7",
  "epubdate": "2026 May 7",
  "source": "Pol Arch Intern Med",
  "authors": [
    {
      "name": "Sobstyl J",
      "authtype": "Author",
      "clusterid": ""
    },
    {
      "name": "Mozga K",
      "authtype": "Author",
      "clusterid": ""
    },
    {
      "name": "Czyżewski W",
      "authtype": "Author",
      "clusterid": ""
    },
    {
      "name": "Litak J",
      "authtype": "Author",
      "clusterid": ""
    },
    {
      "name": "Sojka M",
      "authtype": "Author",
      "clusterid": ""
    }
  ],
  "lastauthor": "Sojka M",
  "title": "Rasmussen aneurysm: minimally-invasive management of a rare complication of recurrent pulmonary tuberculosis.",
  "sorttitle": "rasmussen aneurysm minimally invasive management of a rare complication of recurrent pulmonary tuberculosis",
  "volume": "136",
  "issue": "5",
  "pages": "",
  "lang": [
    "eng"
  ],
  "nlmuniqueid": "101700960",
  "issn": "0032-3772",
  "essn": "1897-9483",
  "pubtype": [
    "Journal Article"
  ],
  "recordstatus": "PubMed - in process",
  "pubstatus": "256",
  "articleids": [
    {
      "idtype": "pubmed",
      "idtypen": 1,
      "value": "42095410"
    },
    {
      "idtype": "doi",
      "idtypen": 3,
      "value": "10.20452/pamw.17295"
    },
    {
      "idtype": "pii",
      "idtypen": 4,
      "value": "17295"
    }
  ],
  "history": [
    {
      "pubstatus": "pubmed",
      "date": "2026/05/07 12:36"
    },
    {
      "pubstatus": "medline",
      "date": "2026/05/07 12:36"
    },
    {
      "pubstatus": "entrez",
      "date": "2026/05/07 06:39"
    }
  ],
  "references": [],
  "attributes": [],
  "pmcrefcount": "",
  "fulljournalname": "Polish archives of internal medicine",
  "elocationid": "pii: 17295. doi: 10.20452/pamw.17295",
  "doctype": "citation",
  "srccontriblist": [],
  "booktitle": "",
  "medium": "",
  "edition": "",
  "publisherlocation": "",
  "publishername": "",
  "srcdate": "",
  "reportnumber": "",
  "availablefromurl": "",
  "locationlabel": "",
  "doccontriblist": [],
  "docdate": "",
  "bookname": "",
  "chapter": "",
  "sortpubdate": "2026/05/07 00:00",
  "sortfirstauthor": "Sobstyl J",
  "vernaculartitle": ""
}