{
  "uid": "19457930",
  "pubdate": "2009 Jul",
  "epubdate": "2009 May 20",
  "source": "J Antimicrob Chemother",
  "authors": [
    {
      "name": "Cuirolo A",
      "authtype": "Author",
      "clusterid": ""
    },
    {
      "name": "Plata K",
      "authtype": "Author",
      "clusterid": ""
    },
    {
      "name": "Rosato AE",
      "authtype": "Author",
      "clusterid": ""
    }
  ],
  "lastauthor": "Rosato AE",
  "title": "Development of homogeneous expression of resistance in methicillin-resistant Staphylococcus aureus clinical strains is functionally associated with a beta-lactam-mediated SOS response.",
  "sorttitle": "development of homogeneous expression of resistance in methicillin resistant staphylococcus aureus clinical strains is functionally associated with a beta lactam mediated sos response",
  "volume": "64",
  "issue": "1",
  "pages": "37-45",
  "lang": [
    "eng"
  ],
  "nlmuniqueid": "7513617",
  "issn": "0305-7453",
  "essn": "1460-2091",
  "pubtype": [
    "Journal Article",
    "Research Support, N.I.H., Extramural",
    "Research Support, Non-U.S. Gov't"
  ],
  "recordstatus": "PubMed - indexed for MEDLINE",
  "pubstatus": "256",
  "articleids": [
    {
      "idtype": "pubmed",
      "idtypen": 1,
      "value": "19457930"
    },
    {
      "idtype": "pmc",
      "idtypen": 8,
      "value": "PMC2721692"
    },
    {
      "idtype": "pmcid",
      "idtypen": 5,
      "value": "pmc-id: PMC2721692;"
    },
    {
      "idtype": "doi",
      "idtypen": 3,
      "value": "10.1093/jac/dkp164"
    },
    {
      "idtype": "pii",
      "idtypen": 4,
      "value": "dkp164"
    }
  ],
  "history": [
    {
      "pubstatus": "entrez",
      "date": "2009/05/22 09:00"
    },
    {
      "pubstatus": "pubmed",
      "date": "2009/05/22 09:00"
    },
    {
      "pubstatus": "medline",
      "date": "2009/07/28 09:00"
    },
    {
      "pubstatus": "pmc-release",
      "date": "2010/07/01 00:00"
    }
  ],
  "references": [],
  "attributes": [
    "Has Abstract"
  ],
  "pmcrefcount": 33,
  "fulljournalname": "The Journal of antimicrobial chemotherapy",
  "elocationid": "doi: 10.1093/jac/dkp164",
  "doctype": "citation",
  "srccontriblist": [],
  "booktitle": "",
  "medium": "",
  "edition": "",
  "publisherlocation": "",
  "publishername": "",
  "srcdate": "",
  "reportnumber": "",
  "availablefromurl": "",
  "locationlabel": "",
  "doccontriblist": [],
  "docdate": "",
  "bookname": "",
  "chapter": "",
  "sortpubdate": "2009/07/01 00:00",
  "sortfirstauthor": "Cuirolo A",
  "vernaculartitle": ""
}