{
  "id": "https://openalex.org/W4244532215",
  "doi": "https://doi.org/10.1016/0022-2313(84)90042-5",
  "title": "Spectroscopy of doubly hydrogen-bonded 7-azaindole. Reinvestigation of the excited state reaction",
  "display_name": "Spectroscopy of doubly hydrogen-bonded 7-azaindole. Reinvestigation of the excited state reaction",
  "publication_year": 1984,
  "publication_date": "1984-01-01",
  "ids": {
    "openalex": "https://openalex.org/W4244532215",
    "doi": "https://doi.org/10.1016/0022-2313(84)90042-5"
  },
  "language": "en",
  "primary_location": {
    "id": "doi:10.1016/0022-2313(84)90042-5",
    "is_oa": false,
    "landing_page_url": "https://doi.org/10.1016/0022-2313(84)90042-5",
    "pdf_url": null,
    "source": {
      "id": "https://openalex.org/S188673600",
      "display_name": "Journal of Luminescence",
      "issn_l": "0022-2313",
      "issn": [
        "0022-2313",
        "1872-7883"
      ],
      "is_oa": false,
      "is_in_doaj": false,
      "is_core": true,
      "host_organization": "https://openalex.org/P4310320990",
      "host_organization_name": "Elsevier BV",
      "host_organization_lineage": [
        "https://openalex.org/P4310320990"
      ],
      "host_organization_lineage_names": [
        "Elsevier BV"
      ],
      "type": "journal"
    },
    "license": null,
    "license_id": null,
    "version": "publishedVersion",
    "is_accepted": true,
    "is_published": true,
    "raw_source_name": "Journal of Luminescence",
    "raw_type": "journal-article"
  },
  "type": "article",
  "indexed_in": [
    "crossref"
  ],
  "open_access": {
    "is_oa": false,
    "oa_status": "closed",
    "oa_url": null,
    "any_repository_has_fulltext": false
  },
  "authorships": [
    {
      "author_position": "first",
      "author": {
        "id": "https://openalex.org/A5060486438",
        "display_name": "H. Bulska",
        "orcid": null
      },
      "institutions": [
        {
          "id": "https://openalex.org/I4210157029",
          "display_name": "Institute of Physical Chemistry",
          "ror": "https://ror.org/05e830h62",
          "country_code": "PL",
          "type": "facility",
          "lineage": [
            "https://openalex.org/I4210157029",
            "https://openalex.org/I99542240"
          ]
        },
        {
          "id": "https://openalex.org/I99542240",
          "display_name": "Polish Academy of Sciences",
          "ror": "https://ror.org/01dr6c206",
          "country_code": "PL",
          "type": "government",
          "lineage": [
            "https://openalex.org/I99542240"
          ]
        }
      ],
      "countries": [
        "PL"
      ],
      "is_corresponding": false,
      "raw_author_name": "H. Bulska",
      "raw_affiliation_strings": [
        "Institute of Physical Chemistry, Polish Academy of Sciences, Kasprzaka 44/52, 01-224 Warsaw, Poland"
      ],
      "raw_orcid": null,
      "affiliations": [
        {
          "raw_affiliation_string": "Institute of Physical Chemistry, Polish Academy of Sciences, Kasprzaka 44/52, 01-224 Warsaw, Poland",
          "institution_ids": [
            "https://openalex.org/I99542240",
            "https://openalex.org/I4210157029"
          ]
        }
      ]
    },
    {
      "author_position": "middle",
      "author": {
        "id": "https://openalex.org/A5101547290",
        "display_name": "Agnieszka Grabowska",
        "orcid": "https://orcid.org/0000-0002-8804-6817"
      },
      "institutions": [
        {
          "id": "https://openalex.org/I4210157029",
          "display_name": "Institute of Physical Chemistry",
          "ror": "https://ror.org/05e830h62",
          "country_code": "PL",
          "type": "facility",
          "lineage": [
            "https://openalex.org/I4210157029",
            "https://openalex.org/I99542240"
          ]
        },
        {
          "id": "https://openalex.org/I99542240",
          "display_name": "Polish Academy of Sciences",
          "ror": "https://ror.org/01dr6c206",
          "country_code": "PL",
          "type": "government",
          "lineage": [
            "https://openalex.org/I99542240"
          ]
        }
      ],
      "countries": [
        "PL"
      ],
      "is_corresponding": false,
      "raw_author_name": "A. Grabowska",
      "raw_affiliation_strings": [
        "Institute of Physical Chemistry, Polish Academy of Sciences, Kasprzaka 44/52, 01-224 Warsaw, Poland"
      ],
      "raw_orcid": null,
      "affiliations": [
        {
          "raw_affiliation_string": "Institute of Physical Chemistry, Polish Academy of Sciences, Kasprzaka 44/52, 01-224 Warsaw, Poland",
          "institution_ids": [
            "https://openalex.org/I99542240",
            "https://openalex.org/I4210157029"
          ]
        }
      ]
    },
    {
      "author_position": "middle",
      "author": {
        "id": "https://openalex.org/A5022330268",
        "display_name": "B. Pakuła",
        "orcid": null
      },
      "institutions": [
        {
          "id": "https://openalex.org/I4210157029",
          "display_name": "Institute of Physical Chemistry",
          "ror": "https://ror.org/05e830h62",
          "country_code": "PL",
          "type": "facility",
          "lineage": [
            "https://openalex.org/I4210157029",
            "https://openalex.org/I99542240"
          ]
        },
        {
          "id": "https://openalex.org/I99542240",
          "display_name": "Polish Academy of Sciences",
          "ror": "https://ror.org/01dr6c206",
          "country_code": "PL",
          "type": "government",
          "lineage": [
            "https://openalex.org/I99542240"
          ]
        }
      ],
      "countries": [
        "PL"
      ],
      "is_corresponding": false,
      "raw_author_name": "B. Pakuła",
      "raw_affiliation_strings": [
        "Institute of Physical Chemistry, Polish Academy of Sciences, Kasprzaka 44/52, 01-224 Warsaw, Poland"
      ],
      "raw_orcid": null,
      "affiliations": [
        {
          "raw_affiliation_string": "Institute of Physical Chemistry, Polish Academy of Sciences, Kasprzaka 44/52, 01-224 Warsaw, Poland",
          "institution_ids": [
            "https://openalex.org/I99542240",
            "https://openalex.org/I4210157029"
          ]
        }
      ]
    },
    {
      "author_position": "middle",
      "author": {
        "id": "https://openalex.org/A5071009818",
        "display_name": "Jerzy Sepioł",
        "orcid": "https://orcid.org/0000-0002-4744-8916"
      },
      "institutions": [
        {
          "id": "https://openalex.org/I4210157029",
          "display_name": "Institute of Physical Chemistry",
          "ror": "https://ror.org/05e830h62",
          "country_code": "PL",
          "type": "facility",
          "lineage": [
            "https://openalex.org/I4210157029",
            "https://openalex.org/I99542240"
          ]
        },
        {
          "id": "https://openalex.org/I99542240",
          "display_name": "Polish Academy of Sciences",
          "ror": "https://ror.org/01dr6c206",
          "country_code": "PL",
          "type": "government",
          "lineage": [
            "https://openalex.org/I99542240"
          ]
        }
      ],
      "countries": [
        "PL"
      ],
      "is_corresponding": false,
      "raw_author_name": "J. Sepioł",
      "raw_affiliation_strings": [
        "Institute of Physical Chemistry, Polish Academy of Sciences, Kasprzaka 44/52, 01-224 Warsaw, Poland"
      ],
      "raw_orcid": null,
      "affiliations": [
        {
          "raw_affiliation_string": "Institute of Physical Chemistry, Polish Academy of Sciences, Kasprzaka 44/52, 01-224 Warsaw, Poland",
          "institution_ids": [
            "https://openalex.org/I99542240",
            "https://openalex.org/I4210157029"
          ]
        }
      ]
    },
    {
      "author_position": "middle",
      "author": {
        "id": "https://openalex.org/A5002136860",
        "display_name": "Jacek Waluk",
        "orcid": "https://orcid.org/0000-0001-5745-583X"
      },
      "institutions": [
        {
          "id": "https://openalex.org/I4210157029",
          "display_name": "Institute of Physical Chemistry",
          "ror": "https://ror.org/05e830h62",
          "country_code": "PL",
          "type": "facility",
          "lineage": [
            "https://openalex.org/I4210157029",
            "https://openalex.org/I99542240"
          ]
        },
        {
          "id": "https://openalex.org/I99542240",
          "display_name": "Polish Academy of Sciences",
          "ror": "https://ror.org/01dr6c206",
          "country_code": "PL",
          "type": "government",
          "lineage": [
            "https://openalex.org/I99542240"
          ]
        }
      ],
      "countries": [
        "PL"
      ],
      "is_corresponding": false,
      "raw_author_name": "J. Waluk",
      "raw_affiliation_strings": [
        "Institute of Physical Chemistry, Polish Academy of Sciences, Kasprzaka 44/52, 01-224 Warsaw, Poland"
      ],
      "raw_orcid": null,
      "affiliations": [
        {
          "raw_affiliation_string": "Institute of Physical Chemistry, Polish Academy of Sciences, Kasprzaka 44/52, 01-224 Warsaw, Poland",
          "institution_ids": [
            "https://openalex.org/I99542240",
            "https://openalex.org/I4210157029"
          ]
        }
      ]
    },
    {
      "author_position": "last",
      "author": {
        "id": "https://openalex.org/A5086390650",
        "display_name": "Urs P. Wild",
        "orcid": null
      },
      "institutions": [],
      "countries": [],
      "is_corresponding": false,
      "raw_author_name": "Urs P. Wild",
      "raw_affiliation_strings": [
        "Physical Chemistry Laboratory, Swiss Federal Institute of Technology, ETH-Zentrum, CH-8092 Zürich, Switzerland"
      ],
      "raw_orcid": null,
      "affiliations": [
        {
          "raw_affiliation_string": "Physical Chemistry Laboratory, Swiss Federal Institute of Technology, ETH-Zentrum, CH-8092 Zürich, Switzerland",
          "institution_ids": []
        }
      ]
    }
  ],
  "institutions": [],
  "countries_distinct_count": 1,
  "institutions_distinct_count": 6,
  "corresponding_author_ids": [],
  "corresponding_institution_ids": [],
  "apc_list": {
    "value": 2530,
    "currency": "USD",
    "value_usd": 2530
  },
  "apc_paid": null,
  "fwci": 0.0,
  "has_fulltext": false,
  "cited_by_count": 6,
  "citation_normalized_percentile": {
    "value": 0.52505712,
    "is_in_top_1_percent": false,
    "is_in_top_10_percent": false
  },
  "cited_by_percentile_year": {
    "min": 90,
    "max": 94
  },
  "biblio": {
    "volume": "29",
    "issue": "1",
    "first_page": "65",
    "last_page": "81"
  },
  "is_retracted": false,
  "is_paratext": false,
  "is_xpac": false,
  "primary_topic": {
    "id": "https://openalex.org/T11129",
    "display_name": "Photochemistry and Electron Transfer Studies",
    "score": 0.9997000098228455,
    "subfield": {
      "id": "https://openalex.org/subfields/1606",
      "display_name": "Physical and Theoretical Chemistry"
    },
    "field": {
      "id": "https://openalex.org/fields/16",
      "display_name": "Chemistry"
    },
    "domain": {
      "id": "https://openalex.org/domains/3",
      "display_name": "Physical Sciences"
    }
  },
  "topics": [
    {
      "id": "https://openalex.org/T11129",
      "display_name": "Photochemistry and Electron Transfer Studies",
      "score": 0.9997000098228455,
      "subfield": {
        "id": "https://openalex.org/subfields/1606",
        "display_name": "Physical and Theoretical Chemistry"
      },
      "field": {
        "id": "https://openalex.org/fields/16",
        "display_name": "Chemistry"
      },
      "domain": {
        "id": "https://openalex.org/domains/3",
        "display_name": "Physical Sciences"
      }
    },
    {
      "id": "https://openalex.org/T11240",
      "display_name": "Luminescence and Fluorescent Materials",
      "score": 0.9980999827384949,
      "subfield": {
        "id": "https://openalex.org/subfields/2505",
        "display_name": "Materials Chemistry"
      },
      "field": {
        "id": "https://openalex.org/fields/25",
        "display_name": "Materials Science"
      },
      "domain": {
        "id": "https://openalex.org/domains/3",
        "display_name": "Physical Sciences"
      }
    },
    {
      "id": "https://openalex.org/T10002",
      "display_name": "Advanced Chemical Physics Studies",
      "score": 0.9962999820709229,
      "subfield": {
        "id": "https://openalex.org/subfields/3107",
        "display_name": "Atomic and Molecular Physics, and Optics"
      },
      "field": {
        "id": "https://openalex.org/fields/31",
        "display_name": "Physics and Astronomy"
      },
      "domain": {
        "id": "https://openalex.org/domains/3",
        "display_name": "Physical Sciences"
      }
    }
  ],
  "keywords": [
    {
      "id": "https://openalex.org/keywords/excited-state",
      "display_name": "Excited state",
      "score": 0.8718783855438232
    },
    {
      "id": "https://openalex.org/keywords/phosphorescence",
      "display_name": "Phosphorescence",
      "score": 0.799562931060791
    },
    {
      "id": "https://openalex.org/keywords/chemistry",
      "display_name": "Chemistry",
      "score": 0.7485837340354919
    },
    {
      "id": "https://openalex.org/keywords/luminescence",
      "display_name": "Luminescence",
      "score": 0.6177236437797546
    },
    {
      "id": "https://openalex.org/keywords/photochemistry",
      "display_name": "Photochemistry",
      "score": 0.5951644778251648
    },
    {
      "id": "https://openalex.org/keywords/polar",
      "display_name": "Polar",
      "score": 0.5924209356307983
    },
    {
      "id": "https://openalex.org/keywords/proton",
      "display_name": "Proton",
      "score": 0.5605089664459229
    },
    {
      "id": "https://openalex.org/keywords/excitation",
      "display_name": "Excitation",
      "score": 0.5368462204933167
    },
    {
      "id": "https://openalex.org/keywords/ground-state",
      "display_name": "Ground state",
      "score": 0.48982903361320496
    },
    {
      "id": "https://openalex.org/keywords/fluorescence",
      "display_name": "Fluorescence",
      "score": 0.4865778684616089
    },
    {
      "id": "https://openalex.org/keywords/spectroscopy",
      "display_name": "Spectroscopy",
      "score": 0.46923524141311646
    },
    {
      "id": "https://openalex.org/keywords/hydrogen",
      "display_name": "Hydrogen",
      "score": 0.4441828429698944
    },
    {
      "id": "https://openalex.org/keywords/physical-chemistry",
      "display_name": "Physical chemistry",
      "score": 0.34715813398361206
    },
    {
      "id": "https://openalex.org/keywords/atomic-physics",
      "display_name": "Atomic physics",
      "score": 0.3187893331050873
    },
    {
      "id": "https://openalex.org/keywords/materials-science",
      "display_name": "Materials science",
      "score": 0.1513039767742157
    },
    {
      "id": "https://openalex.org/keywords/organic-chemistry",
      "display_name": "Organic chemistry",
      "score": 0.08618935942649841
    }
  ],
  "concepts": [
    {
      "id": "https://openalex.org/C181500209",
      "wikidata": "https://www.wikidata.org/wiki/Q215328",
      "display_name": "Excited state",
      "level": 2,
      "score": 0.8718783855438232
    },
    {
      "id": "https://openalex.org/C181817918",
      "wikidata": "https://www.wikidata.org/wiki/Q192275",
      "display_name": "Phosphorescence",
      "level": 3,
      "score": 0.799562931060791
    },
    {
      "id": "https://openalex.org/C185592680",
      "wikidata": "https://www.wikidata.org/wiki/Q2329",
      "display_name": "Chemistry",
      "level": 0,
      "score": 0.7485837340354919
    },
    {
      "id": "https://openalex.org/C148869448",
      "wikidata": "https://www.wikidata.org/wiki/Q184240",
      "display_name": "Luminescence",
      "level": 2,
      "score": 0.6177236437797546
    },
    {
      "id": "https://openalex.org/C75473681",
      "wikidata": "https://www.wikidata.org/wiki/Q188651",
      "display_name": "Photochemistry",
      "level": 1,
      "score": 0.5951644778251648
    },
    {
      "id": "https://openalex.org/C29705727",
      "wikidata": "https://www.wikidata.org/wiki/Q294562",
      "display_name": "Polar",
      "level": 2,
      "score": 0.5924209356307983
    },
    {
      "id": "https://openalex.org/C54516573",
      "wikidata": "https://www.wikidata.org/wiki/Q2294",
      "display_name": "Proton",
      "level": 2,
      "score": 0.5605089664459229
    },
    {
      "id": "https://openalex.org/C83581075",
      "wikidata": "https://www.wikidata.org/wiki/Q1361503",
      "display_name": "Excitation",
      "level": 2,
      "score": 0.5368462204933167
    },
    {
      "id": "https://openalex.org/C69523127",
      "wikidata": "https://www.wikidata.org/wiki/Q4480008",
      "display_name": "Ground state",
      "level": 2,
      "score": 0.48982903361320496
    },
    {
      "id": "https://openalex.org/C91881484",
      "wikidata": "https://www.wikidata.org/wiki/Q191807",
      "display_name": "Fluorescence",
      "level": 2,
      "score": 0.4865778684616089
    },
    {
      "id": "https://openalex.org/C32891209",
      "wikidata": "https://www.wikidata.org/wiki/Q483666",
      "display_name": "Spectroscopy",
      "level": 2,
      "score": 0.46923524141311646
    },
    {
      "id": "https://openalex.org/C512968161",
      "wikidata": "https://www.wikidata.org/wiki/Q556",
      "display_name": "Hydrogen",
      "level": 2,
      "score": 0.4441828429698944
    },
    {
      "id": "https://openalex.org/C147789679",
      "wikidata": "https://www.wikidata.org/wiki/Q11372",
      "display_name": "Physical chemistry",
      "level": 1,
      "score": 0.34715813398361206
    },
    {
      "id": "https://openalex.org/C184779094",
      "wikidata": "https://www.wikidata.org/wiki/Q26383",
      "display_name": "Atomic physics",
      "level": 1,
      "score": 0.3187893331050873
    },
    {
      "id": "https://openalex.org/C192562407",
      "wikidata": "https://www.wikidata.org/wiki/Q228736",
      "display_name": "Materials science",
      "level": 0,
      "score": 0.1513039767742157
    },
    {
      "id": "https://openalex.org/C178790620",
      "wikidata": "https://www.wikidata.org/wiki/Q11351",
      "display_name": "Organic chemistry",
      "level": 1,
      "score": 0.08618935942649841
    },
    {
      "id": "https://openalex.org/C1276947",
      "wikidata": "https://www.wikidata.org/wiki/Q333",
      "display_name": "Astronomy",
      "level": 1,
      "score": 0.0
    },
    {
      "id": "https://openalex.org/C127413603",
      "wikidata": "https://www.wikidata.org/wiki/Q11023",
      "display_name": "Engineering",
      "level": 0,
      "score": 0.0
    },
    {
      "id": "https://openalex.org/C49040817",
      "wikidata": "https://www.wikidata.org/wiki/Q193091",
      "display_name": "Optoelectronics",
      "level": 1,
      "score": 0.0
    },
    {
      "id": "https://openalex.org/C62520636",
      "wikidata": "https://www.wikidata.org/wiki/Q944",
      "display_name": "Quantum mechanics",
      "level": 1,
      "score": 0.0
    },
    {
      "id": "https://openalex.org/C121332964",
      "wikidata": "https://www.wikidata.org/wiki/Q413",
      "display_name": "Physics",
      "level": 0,
      "score": 0.0
    },
    {
      "id": "https://openalex.org/C119599485",
      "wikidata": "https://www.wikidata.org/wiki/Q43035",
      "display_name": "Electrical engineering",
      "level": 1,
      "score": 0.0
    }
  ],
  "mesh": [],
  "locations_count": 1,
  "locations": [
    {
      "id": "doi:10.1016/0022-2313(84)90042-5",
      "is_oa": false,
      "landing_page_url": "https://doi.org/10.1016/0022-2313(84)90042-5",
      "pdf_url": null,
      "source": {
        "id": "https://openalex.org/S188673600",
        "display_name": "Journal of Luminescence",
        "issn_l": "0022-2313",
        "issn": [
          "0022-2313",
          "1872-7883"
        ],
        "is_oa": false,
        "is_in_doaj": false,
        "is_core": true,
        "host_organization": "https://openalex.org/P4310320990",
        "host_organization_name": "Elsevier BV",
        "host_organization_lineage": [
          "https://openalex.org/P4310320990"
        ],
        "host_organization_lineage_names": [
          "Elsevier BV"
        ],
        "type": "journal"
      },
      "license": null,
      "license_id": null,
      "version": "publishedVersion",
      "is_accepted": true,
      "is_published": true,
      "raw_source_name": "Journal of Luminescence",
      "raw_type": "journal-article"
    }
  ],
  "best_oa_location": null,
  "sustainable_development_goals": [
    {
      "score": 0.6800000071525574,
      "display_name": "Affordable and clean energy",
      "id": "https://metadata.un.org/sdg/7"
    }
  ],
  "awards": [],
  "funders": [],
  "has_content": {
    "pdf": false,
    "grobid_xml": false
  },
  "content_urls": null,
  "referenced_works_count": 25,
  "referenced_works": [
    "https://openalex.org/W1508053909",
    "https://openalex.org/W1966688608",
    "https://openalex.org/W1972190287",
    "https://openalex.org/W1979614867",
    "https://openalex.org/W1983718246",
    "https://openalex.org/W1993359480",
    "https://openalex.org/W1993747582",
    "https://openalex.org/W1997164102",
    "https://openalex.org/W2004172986",
    "https://openalex.org/W2005695502",
    "https://openalex.org/W2007826599",
    "https://openalex.org/W2008904237",
    "https://openalex.org/W2017598538",
    "https://openalex.org/W2033091884",
    "https://openalex.org/W2033273145",
    "https://openalex.org/W2034511371",
    "https://openalex.org/W2048210709",
    "https://openalex.org/W2067387505",
    "https://openalex.org/W2076878382",
    "https://openalex.org/W2084135044",
    "https://openalex.org/W2087642369",
    "https://openalex.org/W2136192914",
    "https://openalex.org/W2952412492",
    "https://openalex.org/W3004492947",
    "https://openalex.org/W3004933186"
  ],
  "related_works": [
    "https://openalex.org/W1236873978",
    "https://openalex.org/W2056860351",
    "https://openalex.org/W2579487753",
    "https://openalex.org/W4388702023",
    "https://openalex.org/W2164180279",
    "https://openalex.org/W4248016917",
    "https://openalex.org/W2916457493",
    "https://openalex.org/W4376849493",
    "https://openalex.org/W4384131606",
    "https://openalex.org/W4387985823"
  ],
  "abstract_inverted_index": null,
  "counts_by_year": [
    {
      "year": 2019,
      "cited_by_count": 1
    },
    {
      "year": 2014,
      "cited_by_count": 1
    }
  ],
  "updated_date": "2026-06-11T09:08:48.828518",
  "created_date": "2025-10-10T00:00:00"
}