{
  "uid": "42116185",
  "pubdate": "2026 May 11",
  "epubdate": "2026 May 11",
  "source": "J Cheminform",
  "authors": [
    {
      "name": "Szostek T",
      "authtype": "Author",
      "clusterid": ""
    },
    {
      "name": "Wiśniewski M",
      "authtype": "Author",
      "clusterid": ""
    },
    {
      "name": "Ballabio D",
      "authtype": "Author",
      "clusterid": ""
    },
    {
      "name": "Consonni V",
      "authtype": "Author",
      "clusterid": ""
    },
    {
      "name": "Plewczyński D",
      "authtype": "Author",
      "clusterid": ""
    },
    {
      "name": "Szulczyk D",
      "authtype": "Author",
      "clusterid": ""
    }
  ],
  "lastauthor": "Szulczyk D",
  "title": "De novo design of anticancer 4-thiazolidinone derivatives: a generative framework shaped by activity cliffs.",
  "sorttitle": "de novo design of anticancer 4 thiazolidinone derivatives a generative framework shaped by activity cliffs",
  "volume": "",
  "issue": "",
  "pages": "",
  "lang": [
    "eng"
  ],
  "nlmuniqueid": "101516718",
  "issn": "1758-2946",
  "essn": "",
  "pubtype": [
    "Journal Article"
  ],
  "recordstatus": "PubMed - as supplied by publisher",
  "pubstatus": "10",
  "articleids": [
    {
      "idtype": "pubmed",
      "idtypen": 1,
      "value": "42116185"
    },
    {
      "idtype": "doi",
      "idtypen": 3,
      "value": "10.1186/s13321-026-01216-3"
    },
    {
      "idtype": "pii",
      "idtypen": 4,
      "value": "10.1186/s13321-026-01216-3"
    }
  ],
  "history": [
    {
      "pubstatus": "received",
      "date": "2026/01/13 00:00"
    },
    {
      "pubstatus": "accepted",
      "date": "2026/05/01 00:00"
    },
    {
      "pubstatus": "medline",
      "date": "2026/05/12 06:34"
    },
    {
      "pubstatus": "pubmed",
      "date": "2026/05/12 06:34"
    },
    {
      "pubstatus": "entrez",
      "date": "2026/05/12 00:44"
    }
  ],
  "references": [],
  "attributes": [
    "Has Abstract"
  ],
  "pmcrefcount": "",
  "fulljournalname": "Journal of cheminformatics",
  "elocationid": "doi: 10.1186/s13321-026-01216-3",
  "doctype": "citation",
  "srccontriblist": [],
  "booktitle": "",
  "medium": "",
  "edition": "",
  "publisherlocation": "",
  "publishername": "",
  "srcdate": "",
  "reportnumber": "",
  "availablefromurl": "",
  "locationlabel": "",
  "doccontriblist": [],
  "docdate": "",
  "bookname": "",
  "chapter": "",
  "sortpubdate": "2026/05/11 00:00",
  "sortfirstauthor": "Szostek T",
  "vernaculartitle": ""
}